auto_ner/__init__.py
auto_ner/app.py
auto_ner/run.py
auto_ner-0.1.2.dist-info/LICENSE
auto_ner-0.1.2.dist-info/METADATA
auto_ner-0.1.2.dist-info/WHEEL
auto_ner-0.1.2.dist-info/entry_points.txt
auto_ner-0.1.2.dist-info/top_level.txt
auto_ner-0.1.2.dist-info/RECORD
